arang/__init__.py
arang/clipboard.py
arang/encoding.py
arang/hashing.py
arang/packet.py
arang/crypto/__init__.py
arang/crypto/aes.py
arang/crypto/seed.py
arang-2.0.0.dist-info/METADATA
arang-2.0.0.dist-info/WHEEL
arang-2.0.0.dist-info/top_level.txt
arang-2.0.0.dist-info/RECORD
