Metadata-Version: 2.4
Name: arang
Version: 2.0.0
Summary: Python module for web hacking and security testing
Home-page: https://github.com/JaewookYou/arang
Author: arang
Author-email: jwyou@fsec.or.kr
Keywords: arang,webhacking,security,ctf,crypto
Classifier: Development Status :: 4 - Beta
Classifier: Intended Audience :: Developers
Classifier: Intended Audience :: Information Technology
Classifier: Topic :: Security
Classifier: License :: OSI Approved :: MIT License
Classifier: Programming Language :: Python :: 3
Classifier: Programming Language :: Python :: 3.8
Classifier: Programming Language :: Python :: 3.9
Classifier: Programming Language :: Python :: 3.10
Classifier: Programming Language :: Python :: 3.11
Classifier: Programming Language :: Python :: 3.12
Classifier: Programming Language :: Python :: 3.13
Classifier: Operating System :: OS Independent
Requires-Python: >=3.8
Requires-Dist: requests>=2.25.0
Requires-Dist: pycryptodome>=3.15.0
Requires-Dist: pyperclip>=1.8.0
Provides-Extra: seed
Requires-Dist: kisa-seed>=1.0.0; extra == "seed"
Dynamic: author
Dynamic: author-email
Dynamic: classifier
Dynamic: description
Dynamic: description-content-type
Dynamic: home-page
Dynamic: keywords
Dynamic: provides-extra
Dynamic: requires-dist
Dynamic: requires-python
Dynamic: summary
